balrogclient/__init__.py
balrogclient/api.py
balrogclient-2.0.dist-info/METADATA
balrogclient-2.0.dist-info/WHEEL
balrogclient-2.0.dist-info/licenses/LICENSE
balrogclient-2.0.dist-info/RECORD
